greenlight/__init__.py
greenlight/greenlight.py
signalman/__init__.py
signalman/signalman.py
signalman-0.1.17.dist-info/LICENSE
signalman-0.1.17.dist-info/METADATA
signalman-0.1.17.dist-info/WHEEL
signalman-0.1.17.dist-info/entry_points.txt
signalman-0.1.17.dist-info/top_level.txt
signalman-0.1.17.dist-info/RECORD
