Metadata-Version: 2.1
Name: signalman
Version: 0.1.17
Summary: A small application to poll for response code or text
Home-page: https://github.com/JosephRPalmer/signalman
Author: Joseph Ryan-Palmer
Author-email: joseph@ryan-palmer.com
License: UNKNOWN
Project-URL: Bug Tracker, https://github.com/JosephRPalmer/signalman/issues
Platform: UNKNOWN
Classifier: Programming Language :: Python :: 3
Classifier: License :: OSI Approved :: MIT License
Classifier: Operating System :: OS Independent
Requires-Python: >=3.6
Requires-Dist: requests
Requires-Dist: interruptingcow
Requires-Dist: retrying
